LICENSE.txt
MANIFEST.in
README.rst
setup.cfg
setup.py
onlinepayments/__init__.py
onlinepayments/sdk/__init__.py
onlinepayments/sdk/api_exception.py
onlinepayments/sdk/api_resource.py
onlinepayments/sdk/authorization_exception.py
onlinepayments/sdk/call_context.py
onlinepayments/sdk/client.py
onlinepayments/sdk/communicator.py
onlinepayments/sdk/communicator_configuration.py
onlinepayments/sdk/declined_payment_exception.py
onlinepayments/sdk/declined_payout_exception.py
onlinepayments/sdk/declined_refund_exception.py
onlinepayments/sdk/declined_transaction_exception.py
onlinepayments/sdk/exception_factory.py
onlinepayments/sdk/factory.py
onlinepayments/sdk/i_client.py
onlinepayments/sdk/i_communicator.py
onlinepayments/sdk/idempotence_exception.py
onlinepayments/sdk/platform_exception.py
onlinepayments/sdk/proxy_configuration.py
onlinepayments/sdk/reference_exception.py
onlinepayments/sdk/validation_exception.py
onlinepayments/sdk/authentication/__init__.py
onlinepayments/sdk/authentication/authenticator.py
onlinepayments/sdk/authentication/authorization_type.py
onlinepayments/sdk/authentication/v1hmac_authenticator.py
onlinepayments/sdk/communication/__init__.py
onlinepayments/sdk/communication/communication_exception.py
onlinepayments/sdk/communication/connection.py
onlinepayments/sdk/communication/default_connection.py
onlinepayments/sdk/communication/i_metadata_provider.py
onlinepayments/sdk/communication/metadata_provider.py
onlinepayments/sdk/communication/multipart_form_data_object.py
onlinepayments/sdk/communication/multipart_form_data_request.py
onlinepayments/sdk/communication/not_found_exception.py
onlinepayments/sdk/communication/param_request.py
onlinepayments/sdk/communication/pooled_connection.py
onlinepayments/sdk/communication/request_header.py
onlinepayments/sdk/communication/request_param.py
onlinepayments/sdk/communication/response_exception.py
onlinepayments/sdk/communication/response_header.py
onlinepayments/sdk/domain/__init__.py
onlinepayments_sdk_python3.egg-info/PKG-INFO
onlinepayments_sdk_python3.egg-info/SOURCES.txt
onlinepayments_sdk_python3.egg-info/dependency_links.txt
onlinepayments_sdk_python3.egg-info/requires.txt
onlinepayments_sdk_python3.egg-info/top_level.txt