Metadata-Version: 2.4
Name: onlinepayments-sdk-python3
Version: 6.3.0
Summary: SDK to communicate with the Online Payments platform using the Online Payments Server API
Home-page: https://github.com/wl-online-payments-direct/sdk-python3
Author: Worldline Direct support team
Author-email: 82139942+worldline-direct-support-team@users.noreply.github.com
License: MIT
Keywords: Online Payments SDK
Platform: python 3.7
Classifier: Development Status :: 5 - Production/Stable
Classifier: Operating System :: POSIX :: Linux
Classifier: Operating System :: Microsoft :: Windows
Classifier: Intended Audience :: Developers
Classifier: Programming Language :: Python :: 3 :: Only
Classifier: Programming Language :: Python :: 3.7
Classifier: Programming Language :: Python :: 3.8
Classifier: Programming Language :: Python :: 3.9
Classifier: Programming Language :: Python :: 3.10
Classifier: Programming Language :: Python :: 3.11
Classifier: Programming Language :: Python :: 3.12
Classifier: Programming Language :: Python :: 3.13
Classifier: Topic :: Office/Business :: Financial
Classifier: License :: OSI Approved :: MIT License
Requires-Python: >= 3.7
License-File: LICENSE.txt
Requires-Dist: requests>=2.25.0
Requires-Dist: requests-toolbelt>=0.8.0
Dynamic: author
Dynamic: author-email
Dynamic: classifier
Dynamic: description
Dynamic: description-content-type
Dynamic: home-page
Dynamic: keywords
Dynamic: license
Dynamic: license-file
Dynamic: platform
Dynamic: requires-dist
Dynamic: requires-python
Dynamic: summary
